h8/__init__.py
h8/__main__.py
h8-0.0.2.dist-info/LICENSE
h8-0.0.2.dist-info/METADATA
h8-0.0.2.dist-info/WHEEL
h8-0.0.2.dist-info/top_level.txt
h8-0.0.2.dist-info/RECORD
