Metadata-Version: 2.1
Name: h8
Version: 0.0.2
Summary: The Python Hexagonal (h8) Framework
Author-email: Juan Cerezo <jcerezo.dev@proton.me>
Classifier: Programming Language :: Python :: 3
Requires-Python: >=3.12
License-File: LICENSE
Provides-Extra: ci
Requires-Dist: pre-commit ; extra == 'ci'
Requires-Dist: h8[test] ; extra == 'ci'
Requires-Dist: h8[lint] ; extra == 'ci'
Provides-Extra: dev
Requires-Dist: pre-commit ; extra == 'dev'
Requires-Dist: h8[test] ; extra == 'dev'
Requires-Dist: h8[lint] ; extra == 'dev'
Provides-Extra: lint
Requires-Dist: black ; extra == 'lint'
Requires-Dist: pylint ; extra == 'lint'
Requires-Dist: pyright ; extra == 'lint'
Requires-Dist: isort ; extra == 'lint'
Requires-Dist: autoflake ; extra == 'lint'
Requires-Dist: radon ; extra == 'lint'
Provides-Extra: test
Requires-Dist: pytest ; extra == 'test'
